{
  "schema_version": "0.1.0",
  "project_reference": "LABOTEK-STUDIO-QT",
  "source_file": "Labotek Studio_qt.pdf",
  "quotation_date": "2026-07-22",
  "status": "draft_subject_to_confirmation",
  "currency": "EUR",
  "customer": "TBD",
  "agent": "Labotek Studio",
  "material": "PA6",
  "drying_basis": {
    "throughput_kg_h": 210,
    "temperature_c": 80,
    "residence_time_h": 4.0
  },
  "items": [
    {
      "position": 1,
      "item_number": "101913",
      "description": "DFD 450 machine",
      "quantity": 1,
      "type": "component",
      "family": "DFD",
      "model": "DFD450",
      "source_page": 2,
      "confidence": 1.0
    },
    {
      "position": 2,
      "item_number": "101632",
      "description": "DH1600 machine",
      "quantity": 1,
      "type": "component",
      "family": "DH",
      "model": "DH1600",
      "source_page": 2,
      "confidence": 1.0
    },
    {
      "position": 3,
      "item_number": "TBD",
      "description": "EHR-100 heat recovery machine",
      "quantity": 1,
      "type": "component",
      "family": "EHR",
      "model": "EHR-100",
      "source_page": 2,
      "confidence": 1.0
    },
    {
      "position": 4,
      "item_number": "208042",
      "description": "Catchbox DH15-12000, 3 x 50 mm, manual",
      "quantity": 1,
      "type": "component",
      "family": "CATCHBOX",
      "model": "CATCHBOX-3X50-MANUAL",
      "source_page": 2,
      "confidence": 1.0
    },
    {
      "position": 5,
      "item_number": "TBD",
      "description": "SVR 75 L with dedicated Labotek LT3 blower",
      "quantity": 3,
      "type": "component",
      "family": "SVR_LT_ASSEMBLY",
      "model": "SVR75/LT3",
      "subcomponents": [
        {"family": "SVR", "model": "SVR 75 L"},
        {"family": "LT", "model": "LT3"}
      ],
      "source_page": 2,
      "confidence": 1.0
    },
    {
      "position": 6,
      "item_number": "408201/501304/544015",
      "description": "Three independent Ø50 mm conveying pipe systems, each 30 m with 2 bends",
      "quantity": 3,
      "type": "pipe_system",
      "diameter_mm": 50,
      "length_m_each": 30,
      "bends_each": 2,
      "quoted_pipe_sections_6m_total": 15,
      "quoted_couplings_total": 30,
      "quoted_bends_total": 12,
      "source_page": 1,
      "confidence": 1.0
    },
    {
      "position": 7,
      "item_number": "204539",
      "description": "Cyclone 10 L Ø50 mm",
      "quantity": 1,
      "type": "option",
      "placement_status": "pending_confirmation",
      "source_page": 2,
      "confidence": 1.0
    },
    {
      "position": 8,
      "item_number": "208105",
      "description": "Self-purifying filter LT3-LT6 Ø50 mm",
      "quantity": 1,
      "type": "option",
      "placement_status": "pending_confirmation",
      "source_page": 2,
      "confidence": 1.0
    }
  ],
  "conveying_lines": [
    {
      "line": 1,
      "destination": "EXT 1",
      "material": "PA6",
      "throughput_kg_h": 70,
      "receiver": "SVR8",
      "blower": "SHARED LT4",
      "shared_receiver_count": 3,
      "pipe_diameter_mm": 50,
      "pipe_length_m": 30,
      "bends": 2
    },
    {
      "line": 2,
      "destination": "EXT 2",
      "material": "PA6",
      "throughput_kg_h": 80,
      "receiver": "SVR8",
      "blower": "SHARED LT4",
      "shared_receiver_count": 3,
      "pipe_diameter_mm": 50,
      "pipe_length_m": 30,
      "bends": 2
    },
    {
      "line": 3,
      "destination": "EXT 3",
      "material": "PA6",
      "throughput_kg_h": 50,
      "receiver": "SVR8",
      "blower": "SHARED LT4",
      "shared_receiver_count": 3,
      "pipe_diameter_mm": 50,
      "pipe_length_m": 30,
      "bends": 2
    }
  ],
  "central_conveying_override": {
    "source": "user_approved_redesign",
    "system_type": "Micro Scan",
    "receiver_model": "SVR8",
    "receiver_quantity": 3,
    "shared_receiver_count": 3,
    "central_blower_model": "LT4",
    "central_blower_quantity": 1,
    "destination_component": "EXTRUDER"
  },
  "design_decisions": [
    "The original three SVR 75 L and three LT3 arrangement is superseded by a user-approved central conveying redesign.",
    "Three SVR8 scanning receivers share one vacuum header and one central LT4 blower.",
    "A shared vacuum source with three SVRs is Micro Scan and must never be represented as Con-Evator.",
    "The three manual 50 mm catchbox outlets feed EXT 1, EXT 2 and EXT 3.",
    "The supplied extruder component is used for all three destinations.",
    "The principle routes follow the system-layout value of 2 bends per line; the remaining quoted bends are not assigned without layout confirmation.",
    "Cyclone and filter placement remains pending confirmation."
  ]
}
